odoo10_addon_l10n_th_address-10.0.0.1.0.99.dev2-py2.7-nspkg.pth
odoo/addons/l10n_th_address/README.rst
odoo/addons/l10n_th_address/__init__.py
odoo/addons/l10n_th_address/__manifest__.py
odoo/addons/l10n_th_address/hooks.py
odoo/addons/l10n_th_address/data/res.country.district.csv
odoo/addons/l10n_th_address/data/res.country.province.csv
odoo/addons/l10n_th_address/data/res.country.township.csv
odoo/addons/l10n_th_address/models/__init__.py
odoo/addons/l10n_th_address/models/res_country.py
odoo/addons/l10n_th_address/models/res_partner.py
odoo/addons/l10n_th_address/security/ir.model.access.csv
odoo/addons/l10n_th_address/static/description/icon.png
odoo/addons/l10n_th_address/views/res_country_view.xml
odoo/addons/l10n_th_address/views/res_partner_view.xml
odoo10_addon_l10n_th_address-10.0.0.1.0.99.dev2.dist-info/DESCRIPTION.rst
odoo10_addon_l10n_th_address-10.0.0.1.0.99.dev2.dist-info/METADATA
odoo10_addon_l10n_th_address-10.0.0.1.0.99.dev2.dist-info/RECORD
odoo10_addon_l10n_th_address-10.0.0.1.0.99.dev2.dist-info/WHEEL
odoo10_addon_l10n_th_address-10.0.0.1.0.99.dev2.dist-info/metadata.json
odoo10_addon_l10n_th_address-10.0.0.1.0.99.dev2.dist-info/namespace_packages.txt
odoo10_addon_l10n_th_address-10.0.0.1.0.99.dev2.dist-info/top_level.txt
