Metadata-Version: 2.0
Name: odoo10-addon-l10n-th-address
Version: 10.0.0.1.0.99.dev2
Summary: Partner Address in Thai
Home-page: http://ecosoft.co.th
Author: Ecosoft,Odoo Community Association (OCA)
Author-email: support@odoo-community.org
License: AGPL-3
Platform: UNKNOWN
Classifier: Programming Language :: Python :: 2.7
Classifier: Framework :: Odoo
Classifier: License :: OSI Approved :: GNU Affero General Public License v3
Requires-Dist: odoo (<10.1dev,>=10.0)
